latentsae/__init__.py
latentsae/__version__.py
latentsae/sae.py
latentsae/trainer.py
latentsae/utils/__init__.py
latentsae/utils/config.py
latentsae/utils/data_loader.py
latentsae/utils/eleuther.py
latentsae/utils/kernels.py
latentsae/utils/old_training.py
latentsae/widgets/__init__.py
latentsae/widgets/embedding_vis/__init__.py
latentsae/widgets/embedding_vis/index.css
latentsae/widgets/embedding_vis/index.js
latentsae/widgets/topk_vis/__init__.py
latentsae/widgets/topk_vis/index.css
latentsae/widgets/topk_vis/index.js
latentsae-0.1.3.dist-info/METADATA
latentsae-0.1.3.dist-info/WHEEL
latentsae-0.1.3.dist-info/top_level.txt
latentsae-0.1.3.dist-info/RECORD
