Metadata-Version: 2.1
Name: latentsae
Version: 0.1.3
Summary: LatentSAE: Training and inference for SAEs on embeddings
Home-page: https://github.com/enjalot/latent-sae
License: UNKNOWN
Project-URL: Source, https://github.com/enjalot/latent-sae
Project-URL: Tracker, https://github.com/enjalot/latent-sae/issues
Platform: UNKNOWN
Requires-Dist: torch
Requires-Dist: numpy
Requires-Dist: wandb
Requires-Dist: optuna
Requires-Dist: pyyaml
Requires-Dist: datasets
Requires-Dist: pyarrow
Requires-Dist: tqdm
Requires-Dist: dataclasses
Requires-Dist: simple-parsing
Requires-Dist: einops
Requires-Dist: safetensors
Requires-Dist: accelerate
Requires-Dist: transformers
Requires-Dist: bitsandbytes
Requires-Dist: huggingface-hub
Requires-Dist: ipyreact
